alphainspect/__init__.py
alphainspect/_version.py
alphainspect/calc.py
alphainspect/dtree.py
alphainspect/events.py
alphainspect/ic.py
alphainspect/plotting.py
alphainspect/portfolio.py
alphainspect/reports.py
alphainspect/selection.py
alphainspect/turnover.py
alphainspect/utils.py
alphainspect-0.5.9.dist-info/METADATA
alphainspect-0.5.9.dist-info/WHEEL
alphainspect-0.5.9.dist-info/licenses/LICENSE
alphainspect-0.5.9.dist-info/RECORD
