Metadata-Version: 2.4
Name: alphainspect
Version: 0.5.9
Summary: factor performance visualization
Author-email: wukan <wu-kan@163.com>
License: MIT License
License-File: LICENSE
Keywords: alpha,performance,quant,visualization
Classifier: Development Status :: 4 - Beta
Classifier: Programming Language :: Python
Requires-Python: >=3.8
Requires-Dist: ipykernel
Requires-Dist: loguru
Requires-Dist: matplotlib
Requires-Dist: nbconvert
Requires-Dist: pandas
Requires-Dist: polars-ta
Requires-Dist: pyarrow
Requires-Dist: scipy
Requires-Dist: seaborn
